abci/__init__.py
abci/application.py
abci/encoding.py
abci/server.py
abci/types_pb2.py
abci/utils.py
protobuf/__init__.py
protobuf/github/__init__.py
protobuf/github/com/__init__.py
protobuf/github/com/gogo/__init__.py
protobuf/github/com/gogo/protobuf/__init__.py
protobuf/github/com/gogo/protobuf/gogoproto/__init__.py
protobuf/github/com/gogo/protobuf/gogoproto/gogo_pb2.py
protobuf/github/com/tendermint/__init__.py
protobuf/github/com/tendermint/tendermint/__init__.py
protobuf/github/com/tendermint/tendermint/crypto/__init__.py
protobuf/github/com/tendermint/tendermint/crypto/merkle/__init__.py
protobuf/github/com/tendermint/tendermint/crypto/merkle/merkle_pb2.py
protobuf/github/com/tendermint/tendermint/libs/__init__.py
protobuf/github/com/tendermint/tendermint/libs/common/__init__.py
protobuf/github/com/tendermint/tendermint/libs/common/types_pb2.py
tm_abci-0.6.3.dist-info/LICENSE
tm_abci-0.6.3.dist-info/METADATA
tm_abci-0.6.3.dist-info/WHEEL
tm_abci-0.6.3.dist-info/top_level.txt
tm_abci-0.6.3.dist-info/RECORD
