Metadata-Version: 2.1
Name: tm-abci
Version: 0.6.3
Summary: Python based ABCI Server for Tendermint
Home-page: https://github.com/SoftblocksCo/tm-abci
Author: SoftblocksCo
License: Apache 2.0
Keywords: blockchain tendermint abci
Platform: UNKNOWN
Classifier: Development Status :: 3 - Alpha
Classifier: Intended Audience :: Developers
Classifier: License :: OSI Approved :: Apache Software License
Classifier: Programming Language :: Python :: 3.6
Requires-Python: >=3.6
Requires-Dist: protobuf (>=3.6.1)
Requires-Dist: asyncio (>=3.4.3)
Requires-Dist: colorlog (>=3.1.2)
Requires-Dist: pytest (>=3.5.0)
Requires-Dist: pytest-pythonpath (>=0.7.2)
Requires-Dist: pytest-cov (>=2.5.1)
